[{"id":"107a","posX":897,"posY":927,"neighbors":"waypoint_1","room":null,"type":"endpoint","floor":1},{"id":"106a","posX":897,"posY":948,"neighbors":"waypoint_3","room":null,"type":"endpoint","floor":1},{"id":"105a","posX":897,"posY":975,"neighbors":"waypoint_4","room":null,"type":"endpoint","floor":1},{"id":"104a","posX":897,"posY":999,"neighbors":"waypoint_6","room":null,"type":"endpoint","floor":1},{"id":"103a","posX":897,"posY":1026,"neighbors":"waypoint_8","room":null,"type":"endpoint","floor":1},{"id":"108a","posX":974,"posY":944,"neighbors":"waypoint_2","room":null,"type":"endpoint","floor":1},{"id":"110a","posX":974,"posY":1010,"neighbors":"waypoint_7","room":null,"type":"endpoint","floor":1},{"id":"112a","posX":943,"posY":1149,"neighbors":"waypoint_9","room":null,"type":"endpoint","floor":1},{"id":"113a","posX":970,"posY":1149,"neighbors":"waypoint_11","room":null,"type":"endpoint","floor":1},{"id":"101a","posX":1043,"posY":1150,"neighbors":"waypoint_17","room":null,"type":"endpoint","floor":1},{"id":"114a","posX":1015,"posY":966,"neighbors":"waypoint_15","room":null,"type":"endpoint","floor":1},{"id":"115a","posX":1098,"posY":1046,"neighbors":"waypoint_19","room":null,"type":"endpoint","floor":1},{"id":"117a","posX":1174,"posY":1032,"neighbors":"waypoint_20","room":null,"type":"endpoint","floor":1},{"id":"118a","posX":1256,"posY":1192,"neighbors":"waypoint_39","room":null,"type":"endpoint","floor":1},{"id":"119a","posX":1254,"posY":940,"neighbors":"waypoint_23","room":null,"type":"endpoint","floor":1},{"id":"100b","posX":1345,"posY":1036,"neighbors":"waypoint_25","room":null,"type":"endpoint","floor":1},{"id":"120a","posX":1529,"posY":1194,"neighbors":"waypoint_45","room":null,"type":"endpoint","floor":1},{"id":"121a","posX":1533,"posY":943,"neighbors":"waypoint_40","room":null,"type":"endpoint","floor":1},{"id":"100a","posX":1431,"posY":1035,"neighbors":"waypoint_28","room":null,"type":"endpoint","floor":1},{"id":"122a","posX":1545,"posY":1042,"neighbors":"waypoint_42","room":null,"type":"endpoint","floor":1},{"id":"122b","posX":1628,"posY":1030,"neighbors":"waypoint_32","room":null,"type":"endpoint","floor":1},{"id":"123a","posX":1656,"posY":1030,"neighbors":"waypoint_33","room":null,"type":"endpoint","floor":1},{"id":"124a","posX":1703,"posY":1030,"neighbors":"waypoint_35","room":null,"type":"endpoint","floor":1},{"id":"125a","posX":1737,"posY":1030,"neighbors":"waypoint_36","room":null,"type":"endpoint","floor":1},{"id":"100100","posX":1686,"posY":1106,"neighbors":"waypoint_34","room":null,"type":"endpoint","floor":1},{"id":"waypoint_1","posX":943,"posY":927,"neighbors":"107a waypoint_2","room":null,"type":"waypoint","floor":1},{"id":"waypoint_2","posX":943,"posY":944,"neighbors":"waypoint_1 108a waypoint_3","room":null,"type":"waypoint","floor":1},{"id":"waypoint_3","posX":943,"posY":948,"neighbors":"106a waypoint_2 waypoint_4","room":null,"type":"waypoint","floor":1},{"id":"waypoint_4","posX":943,"posY":975,"neighbors":"waypoint_3 105a waypoint_6","room":null,"type":"waypoint","floor":1},{"id":"waypoint_6","posX":943,"posY":999,"neighbors":"waypoint_4 104a waypoint_7","room":null,"type":"waypoint","floor":1},{"id":"waypoint_7","posX":943,"posY":1010,"neighbors":"110a waypoint_8 waypoint_6","room":null,"type":"waypoint","floor":1},{"id":"waypoint_8","posX":943,"posY":1026,"neighbors":"103a waypoint_7 waypoint_9","room":null,"type":"waypoint","floor":1},{"id":"waypoint_9","posX":943,"posY":1076,"neighbors":"waypoint_8 112a waypoint_11","room":null,"type":"waypoint","floor":1},{"id":"waypoint_11","posX":970,"posY":1076,"neighbors":"waypoint_12 113a waypoint_9","room":null,"type":"waypoint","floor":1},{"id":"waypoint_12","posX":1015,"posY":1076,"neighbors":"waypoint_11 waypoint_13 waypoint_16","room":null,"type":"waypoint","floor":1},{"id":"waypoint_13","posX":1015,"posY":1042,"neighbors":"waypoint_12 waypoint_14","room":null,"type":"waypoint","floor":1},{"id":"waypoint_14","posX":1002,"posY":1037,"neighbors":"waypoint_13 waypoint_15","room":null,"type":"waypoint","floor":1},{"id":"waypoint_15","posX":1015,"posY":1013,"neighbors":"waypoint_14 114a","room":null,"type":"waypoint","floor":1},{"id":"waypoint_16","posX":1043,"posY":1076,"neighbors":"waypoint_12 waypoint_17","room":null,"type":"waypoint","floor":1},{"id":"waypoint_17","posX":1043,"posY":1089,"neighbors":"waypoint_16 101a waypoint_18","room":null,"type":"waypoint","floor":1},{"id":"waypoint_18","posX":1068,"posY":1089,"neighbors":"waypoint_17 waypoint_19","room":null,"type":"waypoint","floor":1},{"id":"waypoint_19","posX":1098,"posY":1081,"neighbors":"waypoint_18 115a waypoint_20","room":null,"type":"waypoint","floor":1},{"id":"waypoint_20","posX":1174,"posY":1081,"neighbors":"waypoint_19 117a waypoint_30","room":null,"type":"waypoint","floor":1},{"id":"waypoint_21","posX":1302,"posY":1081,"neighbors":"waypoint_30 waypoint_24 waypoint_38 waypoint_26","room":null,"type":"waypoint","floor":1},{"id":"waypoint_22","posX":1302,"posY":1000,"neighbors":"waypoint_24 waypoint_23","room":null,"type":"waypoint","floor":1},{"id":"waypoint_23","posX":1254,"posY":1000,"neighbors":"waypoint_22 119a","room":null,"type":"waypoint","floor":1},{"id":"waypoint_24","posX":1302,"posY":1059,"neighbors":"waypoint_21 waypoint_22 waypoint_25","room":null,"type":"waypoint","floor":1},{"id":"waypoint_25","posX":1345,"posY":1059,"neighbors":"waypoint_24 100b","room":null,"type":"waypoint","floor":1},{"id":"waypoint_26","posX":1487,"posY":1081,"neighbors":"waypoint_21 waypoint_27 waypoint_31 waypoint_43","room":null,"type":"waypoint","floor":1},{"id":"waypoint_27","posX":1485,"posY":1057,"neighbors":"waypoint_28 waypoint_26 waypoint_29","room":null,"type":"waypoint","floor":1},{"id":"waypoint_28","posX":1431,"posY":1057,"neighbors":"waypoint_27 100a","room":null,"type":"waypoint","floor":1},{"id":"waypoint_29","posX":1486,"posY":1003,"neighbors":"waypoint_27 waypoint_40","room":null,"type":"waypoint","floor":1},{"id":"waypoint_30","posX":1212,"posY":1081,"neighbors":"waypoint_20 waypoint_21 waypoint_37","room":null,"type":"waypoint","floor":1},{"id":"waypoint_31","posX":1574,"posY":1081,"neighbors":"waypoint_26 waypoint_44 waypoint_46","room":null,"type":"waypoint","floor":1},{"id":"waypoint_32","posX":1628,"posY":1081,"neighbors":"waypoint_33 122b waypoint_46","room":null,"type":"waypoint","floor":1},{"id":"waypoint_33","posX":1657,"posY":1081,"neighbors":"waypoint_32 waypoint_34 123a","room":null,"type":"waypoint","floor":1},{"id":"waypoint_34","posX":1686,"posY":1081,"neighbors":"waypoint_33 waypoint_35 100100","room":null,"type":"waypoint","floor":1},{"id":"waypoint_35","posX":1703,"posY":1081,"neighbors":"waypoint_34 124a waypoint_36","room":null,"type":"waypoint","floor":1},{"id":"waypoint_36","posX":1738,"posY":1081,"neighbors":"waypoint_35 125a","room":null,"type":"waypoint","floor":1},{"id":"waypoint_37","posX":1212,"posY":1131,"neighbors":"waypoint_30 waypoint_39","room":null,"type":"waypoint","floor":1},{"id":"waypoint_38","posX":1303,"posY":1131,"neighbors":"waypoint_39 waypoint_21","room":null,"type":"waypoint","floor":1},{"id":"waypoint_39","posX":1256,"posY":1131,"neighbors":"waypoint_37 waypoint_38 118a","room":null,"type":"waypoint","floor":1},{"id":"waypoint_40","posX":1533,"posY":1003,"neighbors":"waypoint_29 121a waypoint_41","room":null,"type":"waypoint","floor":1},{"id":"waypoint_41","posX":1582,"posY":1003,"neighbors":"waypoint_40 waypoint_42","room":null,"type":"waypoint","floor":1},{"id":"waypoint_42","posX":1585,"posY":1042,"neighbors":"waypoint_41 waypoint_46 122a","room":null,"type":"waypoint","floor":1},{"id":"waypoint_43","posX":1487,"posY":1133,"neighbors":"waypoint_26 waypoint_45","room":null,"type":"waypoint","floor":1},{"id":"waypoint_44","posX":1575,"posY":1133,"neighbors":"waypoint_45 waypoint_31","room":null,"type":"waypoint","floor":1},{"id":"waypoint_45","posX":1530,"posY":1133,"neighbors":"waypoint_43 waypoint_44 120a","room":null,"type":"waypoint","floor":1},{"id":"waypoint_46","posX":1585,"posY":1081,"neighbors":"waypoint_31 waypoint_42 waypoint_32","room":null,"type":"waypoint","floor":1},{"id":"201a","posX":900,"posY":946,"neighbors":"waypoint_47","room":null,"type":"endpoint","floor":2},{"id":"202a","posX":952,"posY":1155,"neighbors":"waypoint_48","room":null,"type":"endpoint","floor":2},{"id":"203a","posX":994,"posY":1155,"neighbors":"waypoint_49","room":null,"type":"endpoint","floor":2},{"id":"204a","posX":1019,"posY":1155,"neighbors":"waypoint_50","room":null,"type":"endpoint","floor":2},{"id":"209a","posX":1125,"posY":1030,"neighbors":"waypoint_51","room":null,"type":"endpoint","floor":2},{"id":"211a","posX":1148,"posY":1030,"neighbors":"waypoint_52","room":null,"type":"endpoint","floor":2},{"id":"213a","posX":1179,"posY":1031,"neighbors":"waypoint_55","room":null,"type":"endpoint","floor":2},{"id":"215a","posX":1207,"posY":1031,"neighbors":"waypoint_56","room":null,"type":"endpoint","floor":2},{"id":"217a","posX":1230,"posY":1031,"neighbors":"waypoint_57","room":null,"type":"endpoint","floor":2},{"id":"200100","posX":1160,"posY":1103,"neighbors":"waypoint_53","room":null,"type":"endpoint","floor":2},{"id":"218a","posX":1308,"posY":1031,"neighbors":"waypoint_58","room":null,"type":"endpoint","floor":2},{"id":"219a","posX":1381,"posY":1031,"neighbors":"waypoint_60","room":null,"type":"endpoint","floor":2},{"id":"234a","posX":1358,"posY":1107,"neighbors":"waypoint_59","room":null,"type":"endpoint","floor":2},{"id":"233a","posX":1395,"posY":1107,"neighbors":"waypoint_61","room":null,"type":"endpoint","floor":2},{"id":"232a","posX":1430,"posY":1107,"neighbors":"waypoint_63","room":null,"type":"endpoint","floor":2},{"id":"220a","posX":1409,"posY":1031,"neighbors":"waypoint_62","room":null,"type":"endpoint","floor":2},{"id":"221a","posX":1456,"posY":1031,"neighbors":"waypoint_64","room":null,"type":"endpoint","floor":2},{"id":"222a","posX":1481,"posY":1031,"neighbors":"waypoint_65","room":null,"type":"endpoint","floor":2},{"id":"223a","posX":1531,"posY":1031,"neighbors":"waypoint_66","room":null,"type":"endpoint","floor":2},{"id":"224a","posX":1558,"posY":1031,"neighbors":"waypoint_67","room":null,"type":"endpoint","floor":2},{"id":"225a","posX":1608,"posY":1031,"neighbors":"waypoint_68","room":null,"type":"endpoint","floor":2},{"id":"231a","posX":1625,"posY":1108,"neighbors":"waypoint_70","room":null,"type":"endpoint","floor":2},{"id":"226a","posX":1632,"posY":1031,"neighbors":"waypoint_69","room":null,"type":"endpoint","floor":2},{"id":"227a","posX":1659,"posY":1055,"neighbors":"waypoint_73","room":null,"type":"endpoint","floor":2},{"id":"228a","posX":1709,"posY":1045,"neighbors":"229a","room":null,"type":"endpoint","floor":2},{"id":"229a","posX":1736,"posY":1045,"neighbors":"waypoint_74 228a","room":null,"type":"endpoint","floor":2},{"id":"230a","posX":1658,"posY":1108,"neighbors":"waypoint_71","room":null,"type":"endpoint","floor":2},{"id":"waypoint_47","posX":900,"posY":1078,"neighbors":"201a waypoint_48","room":null,"type":"waypoint","floor":2},{"id":"waypoint_48","posX":952,"posY":1078,"neighbors":"waypoint_47 202a waypoint_49","room":null,"type":"waypoint","floor":2},{"id":"waypoint_49","posX":994,"posY":1078,"neighbors":"waypoint_48 203a waypoint_50","room":null,"type":"waypoint","floor":2},{"id":"waypoint_50","posX":1019,"posY":1078,"neighbors":"waypoint_49 204a waypoint_51","room":null,"type":"waypoint","floor":2},{"id":"waypoint_51","posX":1125,"posY":1078,"neighbors":"waypoint_50 209a waypoint_54","room":null,"type":"waypoint","floor":2},{"id":"waypoint_52","posX":1148,"posY":1078,"neighbors":"waypoint_54 211a waypoint_55","room":null,"type":"waypoint","floor":2},{"id":"waypoint_53","posX":1140,"posY":1103,"neighbors":"waypoint_54 200100","room":null,"type":"waypoint","floor":2},{"id":"waypoint_54","posX":1140,"posY":1078,"neighbors":"waypoint_51 waypoint_53 waypoint_52","room":null,"type":"waypoint","floor":2},{"id":"waypoint_55","posX":1179,"posY":1078,"neighbors":"waypoint_52 213a waypoint_56","room":null,"type":"waypoint","floor":2},{"id":"waypoint_56","posX":1207,"posY":1078,"neighbors":"waypoint_55 215a waypoint_57","room":null,"type":"waypoint","floor":2},{"id":"waypoint_57","posX":1230,"posY":1078,"neighbors":"waypoint_56 217a waypoint_58","room":null,"type":"waypoint","floor":2},{"id":"waypoint_58","posX":1308,"posY":1078,"neighbors":"waypoint_57 218a waypoint_59","room":null,"type":"waypoint","floor":2},{"id":"waypoint_59","posX":1358,"posY":1078,"neighbors":"waypoint_58 234a waypoint_60","room":null,"type":"waypoint","floor":2},{"id":"waypoint_60","posX":1381,"posY":1078,"neighbors":"waypoint_59 219a waypoint_61","room":null,"type":"waypoint","floor":2},{"id":"waypoint_61","posX":1395,"posY":1078,"neighbors":"waypoint_60 233a waypoint_62","room":null,"type":"waypoint","floor":2},{"id":"waypoint_62","posX":1409,"posY":1078,"neighbors":"waypoint_61 220a waypoint_63","room":null,"type":"waypoint","floor":2},{"id":"waypoint_63","posX":1430,"posY":1078,"neighbors":"waypoint_62 232a waypoint_64","room":null,"type":"waypoint","floor":2},{"id":"waypoint_64","posX":1456,"posY":1078,"neighbors":"waypoint_63 221a waypoint_65","room":null,"type":"waypoint","floor":2},{"id":"waypoint_65","posX":1481,"posY":1078,"neighbors":"222a waypoint_64 waypoint_66","room":null,"type":"waypoint","floor":2},{"id":"waypoint_66","posX":1531,"posY":1078,"neighbors":"waypoint_65 223a waypoint_67","room":null,"type":"waypoint","floor":2},{"id":"waypoint_67","posX":1558,"posY":1078,"neighbors":"waypoint_66 224a waypoint_68","room":null,"type":"waypoint","floor":2},{"id":"waypoint_68","posX":1608,"posY":1078,"neighbors":"waypoint_67 225a waypoint_70","room":null,"type":"waypoint","floor":2},{"id":"waypoint_69","posX":1632,"posY":1078,"neighbors":"waypoint_70 226a waypoint_71","room":null,"type":"waypoint","floor":2},{"id":"waypoint_70","posX":1625,"posY":1078,"neighbors":"waypoint_68 231a waypoint_69","room":null,"type":"waypoint","floor":2},{"id":"waypoint_71","posX":1658,"posY":1078,"neighbors":"waypoint_69 waypoint_72 230a","room":null,"type":"waypoint","floor":2},{"id":"waypoint_72","posX":1681,"posY":1078,"neighbors":"waypoint_71 waypoint_73 waypoint_74","room":null,"type":"waypoint","floor":2},{"id":"waypoint_73","posX":1681,"posY":1055,"neighbors":"waypoint_72 227a","room":null,"type":"waypoint","floor":2},{"id":"waypoint_74","posX":1736,"posY":1078,"neighbors":"waypoint_72 229a","room":null,"type":"waypoint","floor":2},{"id":"306a","posX":1066,"posY":1034,"neighbors":"waypoint_76","room":null,"type":"endpoint","floor":3},{"id":"301a","posX":1066,"posY":1095,"neighbors":"waypoint_76","room":null,"type":"endpoint","floor":3},{"id":"301k","posX":896,"posY":1090,"neighbors":"waypoint_75","room":null,"type":"endpoint","floor":3},{"id":"waypoint_75","posX":896,"posY":1071,"neighbors":"301k waypoint_76","room":null,"type":"waypoint","floor":3},{"id":"waypoint_76","posX":1066,"posY":1072,"neighbors":"waypoint_75 301a 306a","room":null,"type":"waypoint","floor":3}]